aws/osml/tile_server/__init__.py
aws/osml/tile_server/app_config.py
aws/osml/tile_server/main.py
aws/osml/tile_server/ogc/__init__.py
aws/osml/tile_server/ogc/common_core.py
aws/osml/tile_server/ogc/common_geodata.py
aws/osml/tile_server/ogc/tms.py
aws/osml/tile_server/utils/__init__.py
aws/osml/tile_server/utils/aws_services.py
aws/osml/tile_server/utils/health_check.py
aws/osml/tile_server/utils/log_tools.py
aws/osml/tile_server/utils/string_enums.py
aws/osml/tile_server/utils/tile_server_utils.py
aws/osml/tile_server/utils/token.py
aws/osml/tile_server/viewpoint/__init__.py
aws/osml/tile_server/viewpoint/database.py
aws/osml/tile_server/viewpoint/models.py
aws/osml/tile_server/viewpoint/queue.py
aws/osml/tile_server/viewpoint/routers.py
aws/osml/tile_server/viewpoint/worker.py
osml_tile_server-0.3.0.dist-info/LICENSE
osml_tile_server-0.3.0.dist-info/METADATA
osml_tile_server-0.3.0.dist-info/WHEEL
osml_tile_server-0.3.0.dist-info/top_level.txt
osml_tile_server-0.3.0.dist-info/RECORD
