Metadata-Version: 2.1
Name: osml-tile-server
Version: 0.3.0
Summary: The OversightML Tile Server is a lightweight, cloud-based tile server which allows you to quickly pass an image from S3 bucket to get metadata, image statistics, and set of tiles in real-time.
Author: Amazon Web Services
Author-email: aws-osml-admin@amazon.com
License: 
Project-URL: Source, https://github.com/aws-solutions-library-samples/osml-tile-server
Project-URL: Tracker, https://github.com/aws-solutions-library-samples/osml-tile-server/issues
Classifier: Programming Language :: Python :: 3
Classifier: Operating System :: OS Independent
Requires-Python: >=3.9
License-File: LICENSE
Requires-Dist: uvicorn
Requires-Dist: fastapi
Requires-Dist: fastapi-versioning
Requires-Dist: asgi-correlation-id
Requires-Dist: starlette[full]
Requires-Dist: cryptography
Requires-Dist: boto3
Requires-Dist: geojson >=3.0.0
Requires-Dist: pydantic >=2.0.0
Requires-Dist: python-json-logger >=2.0.0
Requires-Dist: osml-imagery-toolkit >=1.4.0rc1
Provides-Extra: test
Requires-Dist: tox ; extra == 'test'
